_reusable/__init__.py
_reusable/elapsed.py
_reusable/node.py
_reusable/one_time_flag.py
tools/__init__.py
tools/chain_path.py
tools/elapsed.py
tools/type_factory.py
tools/welford.py
wiretap/__init__.py
wiretap/activity.py
wiretap/context.py
wiretap/layers.py
wiretap/loggers.py
wiretap/tag.py
wiretap/telemetry.py
wiretap/wiretap.py
wiretap/contexts/__init__.py
wiretap/contexts/activity.py
wiretap/contexts/iteration.py
wiretap/contexts/procedure.py
wiretap/core/__init__.py
wiretap/core/span.py
wiretap/core/logging/__init__.py
wiretap/core/logging/json_encoders.py
wiretap/core/logging/json_formatter.py
wiretap/core/logging/json_modifiers.py
wiretap/core/logging/text_formatter.py
wiretap/core/loops/__init__.py
wiretap/core/loops/loop_rates.py
wiretap/core/loops/loop_stats.py
wiretap/data/__init__.py
wiretap/data/data.py
wiretap/filters/__init__.py
wiretap/filters/add_current_activity.py
wiretap/filters/add_default_activity.py
wiretap/filters/add_extra_const.py
wiretap/filters/add_extra_indent.py
wiretap/filters/add_extra_timestamp.py
wiretap/filters/dump_exception.py
wiretap/filters/filters.py
wiretap/filters/strip_exc_info.py
wiretap/formatters/__init__.py
wiretap/formatters/json_formatter.py
wiretap/formatters/text_formatter.py
wiretap/helpers/__init__.py
wiretap/home/__init__.py
wiretap/home/begin.py
wiretap/home/log.py
wiretap/home/messages.py
wiretap/home/scopes.py
wiretap/json/__init__.py
wiretap/json/encoders.py
wiretap/json/json_multi_encoder.py
wiretap/json/middleware.py
wiretap/json/properties.py
wiretap/meta/__init__.py
wiretap/process/__init__.py
wiretap/process/activity.py
wiretap/process/elapsed.py
wiretap/process/node.py
wiretap/scopes/__init__.py
wiretap/scopes/activity.py
wiretap/scopes/iteration_scope.py
wiretap/scopes/loop.py
wiretap/scopes/telemetry_scope.py
wiretap/specs/__init__.py
wiretap/stats/__init__.py
wiretap/stats/basic.py
wiretap/stats/welford.py
wiretap/tools/__init__.py
wiretap/tools/json_multi_encoder.py
wiretap/types/__init__.py
wiretap-12.1.0.dist-info/METADATA
wiretap-12.1.0.dist-info/WHEEL
wiretap-12.1.0.dist-info/top_level.txt
wiretap-12.1.0.dist-info/RECORD
