Metadata-Version: 2.4
Name: wiretap
Version: 12.1.0
Summary: This package provides a context-oriented logger.
Author: he-dev
Project-URL: GitHub, https://github.com/he-dev/wiretap-py
Classifier: Development Status :: 5 - Production/Stable
Classifier: Intended Audience :: Developers
Classifier: Programming Language :: Python :: 3.10
Classifier: Topic :: Utilities
Requires-Python: >=3.10
Dynamic: requires-python
